README.md
pyproject.toml
setup.py
maskllm_py/resolver.py
maskllm_py.egg-info/PKG-INFO
maskllm_py.egg-info/SOURCES.txt
maskllm_py.egg-info/dependency_links.txt
maskllm_py.egg-info/top_level.txt