Metadata-Version: 2.1
Name: maskllm-py
Version: 0.1.0
Summary: Python SDK for MaskLLM
Home-page: https://github.com/mwpnava/Python-Code/tree/master/My_own_Python_package
Author: MaskLLM Developers
Author-email: admin@maskllm.com
Classifier: Programming Language :: Python :: 3
Classifier: License :: OSI Approved :: MIT License
Classifier: Operating System :: OS Independent
Requires-Python: >=3.6
